odoo/addons/website_product_document_download_counter/README.rst
odoo/addons/website_product_document_download_counter/__init__.py
odoo/addons/website_product_document_download_counter/__manifest__.py
odoo/addons/website_product_document_download_counter/controllers/__init__.py
odoo/addons/website_product_document_download_counter/controllers/main.py
odoo/addons/website_product_document_download_counter/i18n/it.po
odoo/addons/website_product_document_download_counter/i18n/pt_BR.po
odoo/addons/website_product_document_download_counter/i18n/website_product_document_download_counter.pot
odoo/addons/website_product_document_download_counter/models/__init__.py
odoo/addons/website_product_document_download_counter/models/product_document.py
odoo/addons/website_product_document_download_counter/readme/CONTEXT.md
odoo/addons/website_product_document_download_counter/readme/CONTRIBUTORS.md
odoo/addons/website_product_document_download_counter/readme/DESCRIPTION.md
odoo/addons/website_product_document_download_counter/readme/USAGE.md
odoo/addons/website_product_document_download_counter/static/description/icon.png
odoo/addons/website_product_document_download_counter/static/description/index.html
odoo/addons/website_product_document_download_counter/static/description/img/activate-download-counter.png
odoo/addons/website_product_document_download_counter/static/description/img/product-in-website.png
odoo/addons/website_product_document_download_counter/tests/__init__.py
odoo/addons/website_product_document_download_counter/tests/product_document_test_utils.py
odoo/addons/website_product_document_download_counter/tests/test_product_document_http.py
odoo/addons/website_product_document_download_counter/tests/test_product_document_model.py
odoo/addons/website_product_document_download_counter/views/documents.xml
odoo/addons/website_product_document_download_counter/views/product_document_views.xml
odoo_addon_website_product_document_download_counter-18.0.1.0.0.5.dist-info/METADATA
odoo_addon_website_product_document_download_counter-18.0.1.0.0.5.dist-info/WHEEL
odoo_addon_website_product_document_download_counter-18.0.1.0.0.5.dist-info/top_level.txt
odoo_addon_website_product_document_download_counter-18.0.1.0.0.5.dist-info/RECORD
