Metadata-Version: 2.1
Name: odoo-addon-website_product_document_download_counter
Version: 18.0.1.0.0.5
Requires-Python: >=3.10
Requires-Dist: odoo==18.0.*
Summary: Counts the product document downloads from the website.
Home-page: https://github.com/OCA/website
License: LGPL-3
Author: =?utf-8?q?Cetmix_O=C3=9C=2C_Odoo_Community_Association_=28OCA=29?=
Author-email: support@odoo-community.org
Classifier: Programming Language :: Python
Classifier: Framework :: Odoo
Classifier: Framework :: Odoo :: 18.0
Classifier: License :: OSI Approved :: GNU Lesser General Public License v3 (LGPLv3)
